README.rst
setup.py
cmddocs/__init__.py
cmddocs/articles.py
cmddocs/completions.py
cmddocs/rendering.py
cmddocs/utils.py
cmddocs/version.py
cmddocs.egg-info/PKG-INFO
cmddocs.egg-info/SOURCES.txt
cmddocs.egg-info/dependency_links.txt
cmddocs.egg-info/entry_points.txt
cmddocs.egg-info/requires.txt
cmddocs.egg-info/top_level.txt
cmddocs.egg-info/zip-safe