Metadata-Version: 1.1
Name: cmddocs
Version: 0.17.0
Summary: An interactive commandline interface for your personal docs using python, Cmd, git and markdown
Home-page: https://github.com/noqqe/cmddocs
Author: Florian Baumann
Author-email: flo@noqqe.de
License: MIT
Keywords: markdown wiki commandline git
Platform: UNKNOWN
Classifier: Development Status :: 4 - Beta
Classifier: Topic :: Utilities
Classifier: Topic :: Terminals
Classifier: License :: OSI Approved :: MIT License
Classifier: Programming Language :: Python :: 2.7
Classifier: Programming Language :: Python :: 3.5
